imap_data_access/__init__.py
imap_data_access/cli.py
imap_data_access/file_validation.py
imap_data_access/io.py
imap_data_access/processing_input.py
imap_data_access/webpoda.py
imap_data_access-0.37.1.dist-info/licenses/LICENSE
imap_data_access-0.37.1.dist-info/METADATA
imap_data_access-0.37.1.dist-info/WHEEL
imap_data_access-0.37.1.dist-info/entry_points.txt
imap_data_access-0.37.1.dist-info/top_level.txt
imap_data_access-0.37.1.dist-info/RECORD
