Metadata-Version: 2.4
Name: imap-data-access
Version: 0.37.1
Summary: IMAP SDC Data Access
Author-email: IMAP SDC Developers <imap-sdc@lists.lasp.colorado.edu>
License-Expression: MIT
Project-URL: homepage, https://github.com/IMAP-Science-Operations-Center
Project-URL: repository, https://github.com/IMAP-Science-Operations-Center/imap-data-access
Keywords: IMAP,SDC,SOC,SDS,Science Operations
Classifier: Development Status :: 3 - Alpha
Classifier: Natural Language :: English
Classifier: Programming Language :: Python :: 3
Classifier: Programming Language :: Python :: 3.9
Classifier: Programming Language :: Python :: 3.10
Classifier: Programming Language :: Python :: 3.11
Classifier: Programming Language :: Python :: 3.12
Classifier: Programming Language :: Python :: 3.13
Classifier: Topic :: Software Development
Classifier: Topic :: Scientific/Engineering
Classifier: Operating System :: Microsoft :: Windows
Classifier: Operating System :: POSIX
Classifier: Operating System :: Unix
Classifier: Operating System :: MacOS
License-File: LICENSE
Requires-Dist: requests>=2.29
Provides-Extra: dev
Requires-Dist: imap_data_access[test]; extra == "dev"
Requires-Dist: pre-commit; extra == "dev"
Requires-Dist: ruff; extra == "dev"
Provides-Extra: test
Requires-Dist: pytest; extra == "test"
Requires-Dist: pytest-cov; extra == "test"
Dynamic: license-file
